{
	"name":"SceneCavern",
	"id":"SCENE_ID_CAVERN",
	"destinationFilePath":"src/scenes/Cavern.X68",
	"tilesetNames":[
		"TransparentTile",
		"FloorCarpetBlacklight",
		"FrameRect",
		"Glass",
		"TransparentTile",
		"CavernSign",
		"CavernArcadeBase00",
		"CavernArcadeBase01",
		"CavernArcadeBase02",
		"CavernArcadeTop00",
		"CavernArcadeTop01",
		"CavernArcadeTop02"
	],
	"paletteNames":[
		"PaletteCavern00",
		"PaletteCavern01",
		"PaletteCavern02",
		"PalettePeople"
	],
	"scenery":[
		{
			"patternName":"Pattern32x32Tile",
			"comment":"floor",
			"tilesetIndex":1,
			"highPriority":false,
			"paletteNumber":0,
			"repeat":6,
			"layer":"VDP_VRAM_WRITE_B",
			"row":"00000000",
			"column":"00000000"
		},
		{
			"patternName":"PatternFrameTopOpenLeft",
			"comment":"north wall - left side",
			"tilesetIndex":2,
			"highPriority":true,
			"paletteNumber":0,
			"repeat":0,
			"layer":"VDP_VRAM_WRITE_A",
			"row":"00000000",
			"column":"00000000"
		},
		{
			"patternName":"PatternFrameTopOpenRight",
			"comment":"north wall - right side",
			"tilesetIndex":2,
			"highPriority":true,
			"paletteNumber":0,
			"repeat":0,
			"layer":"VDP_VRAM_WRITE_A",
			"column":"00360000",
			"row":"00000000"
		},
		{
			"patternName":"PatternFrameSideClosedRight",
			"comment":"right wall",
			"tilesetIndex":2,
			"highPriority":false,
			"paletteNumber":0,
			"repeat":0,
			"layer":"VDP_VRAM_WRITE_B",
			"row":"00800000",
			"column":"004E0000"
		},
		{
			"patternName":"PatternFrameSideClosedLeft",
			"comment":"left wall",
			"tilesetIndex":2,
			"highPriority":false,
			"paletteNumber":0,
			"repeat":0,
			"layer":"VDP_VRAM_WRITE_B",
			"row":"00800000",
			"column":"00000000"
		},
		{
			"patternName":"PatternStoreFront",
			"comment":"store front",
			"tilesetIndex":2,
			"highPriority":true,
			"paletteNumber":0,
			"repeat":0,
			"layer":"VDP_VRAM_WRITE_A",
			"row":"0C000000",
			"column":"00000000"
		},
		{
			"patternName":"PatternCavernSign",
			"comment":"sign",
			"tilesetIndex":5,
			"highPriority":true,
			"paletteNumber":0,
			"repeat":0,
			"layer":"VDP_VRAM_WRITE_A",
			"row":"0C000000",
			"column":"001A0000"
		},
		{
			"patternName":"Pattern24x24",
			"comment":"pattern 0 - palette 0 - base",
			"tilesetIndex":6,
			"highPriority":false,
			"paletteNumber":0,
			"repeat":0,
			"layer":"VDP_VRAM_WRITE_A",
			"row":"0A000000",
			"column":"00020000"
		},
		{
			"patternName":"Pattern24x24",
			"comment":"pattern 0 - palette 0 - base",
			"tilesetIndex":6,
			"highPriority":false,
			"paletteNumber":0,
			"repeat":0,
			"layer":"VDP_VRAM_WRITE_A",
			"row":"0A000000",
			"column":"00080000"
		},
		{
			"patternName":"Pattern24x24",
			"comment":"pattern 0 - palette 1 - base",
			"tilesetIndex":6,
			"highPriority":false,
			"paletteNumber":1,
			"repeat":0,
			"layer":"VDP_VRAM_WRITE_A",
			"row":"02000000",
			"column":"00420000"
		},
		{
			"patternName":"Pattern24x24",
			"comment":"pattern 0 - palette 1 - base",
			"tilesetIndex":6,
			"highPriority":false,
			"paletteNumber":1,
			"repeat":0,
			"layer":"VDP_VRAM_WRITE_A",
			"row":"02000000",
			"column":"00480000"
		},
		{
			"patternName":"Pattern24x24",
			"comment":"pattern 0 - palette 2 - base",
			"tilesetIndex":6,
			"highPriority":false,
			"paletteNumber":2,
			"repeat":0,
			"layer":"VDP_VRAM_WRITE_A",
			"row":"02000000",
			"column":"000E0000"
		},
		{
			"patternName":"Pattern24x24",
			"comment":"pattern 0 - palette 2 - base",
			"tilesetIndex":6,
			"highPriority":false,
			"paletteNumber":2,
			"repeat":0,
			"layer":"VDP_VRAM_WRITE_A",
			"row":"02000000",
			"column":"00140000"
		},
		{
			"patternName":"Pattern24x24",
			"comment":"pattern 1 - palette 0 - base",
			"tilesetIndex":7,
			"highPriority":false,
			"paletteNumber":0,
			"repeat":0,
			"layer":"VDP_VRAM_WRITE_A",
			"row":"06000000",
			"column":"00360000"
		},
		{
			"patternName":"Pattern24x24",
			"comment":"pattern 1 - palette 0 - base",
			"tilesetIndex":7,
			"highPriority":false,
			"paletteNumber":0,
			"repeat":0,
			"layer":"VDP_VRAM_WRITE_A",
			"row":"06000000",
			"column":"003C0000"
		},
		{
			"patternName":"Pattern24x24",
			"comment":"pattern 1 - palette 1 - base",
			"tilesetIndex":7,
			"highPriority":false,
			"paletteNumber":1,
			"repeat":0,
			"layer":"VDP_VRAM_WRITE_A",
			"row":"02000000",
			"column":"00020000"
		},
		{
			"patternName":"Pattern24x24",
			"comment":"pattern 1 - palette 1 - base",
			"tilesetIndex":7,
			"highPriority":false,
			"paletteNumber":1,
			"repeat":0,
			"layer":"VDP_VRAM_WRITE_A",
			"row":"02000000",
			"column":"00080000"
		},
		{
			"patternName":"Pattern24x24",
			"comment":"pattern 1 - palette 2 - base",
			"tilesetIndex":7,
			"highPriority":false,
			"paletteNumber":2,
			"repeat":0,
			"layer":"VDP_VRAM_WRITE_A",
			"row":"06000000",
			"column":"000E0000"
		},
		{
			"patternName":"Pattern24x24",
			"comment":"pattern 1 - palette 2 - base",
			"tilesetIndex":7,
			"highPriority":false,
			"paletteNumber":2,
			"repeat":0,
			"layer":"VDP_VRAM_WRITE_A",
			"row":"06000000",
			"column":"00140000"
		},
		{
			"patternName":"Pattern24x24",
			"comment":"pattern 2 - palette 0 - base",
			"tilesetIndex":8,
			"highPriority":false,
			"paletteNumber":0,
			"repeat":0,
			"layer":"VDP_VRAM_WRITE_A",
			"row":"02000000",
			"column":"00360000"
		},
		{
			"patternName":"Pattern24x24",
			"comment":"pattern 2 - palette 0 - base",
			"tilesetIndex":8,
			"highPriority":false,
			"paletteNumber":0,
			"repeat":0,
			"layer":"VDP_VRAM_WRITE_A",
			"row":"02000000",
			"column":"003C0000"
		},
		{
			"patternName":"Pattern24x24",
			"comment":"pattern 2 - palette 1 - base",
			"tilesetIndex":8,
			"highPriority":false,
			"paletteNumber":1,
			"repeat":0,
			"layer":"VDP_VRAM_WRITE_A",
			"row":"06000000",
			"column":"00220000"
		},
		{
			"patternName":"Pattern24x24",
			"comment":"pattern 2 - palette 1 - base",
			"tilesetIndex":8,
			"highPriority":false,
			"paletteNumber":1,
			"repeat":0,
			"layer":"VDP_VRAM_WRITE_A",
			"row":"06000000",
			"column":"00280000"
		},
		{
			"patternName":"Pattern24x24",
			"comment":"pattern 2 - palette 2 - base",
			"tilesetIndex":8,
			"highPriority":false,
			"paletteNumber":2,
			"repeat":0,
			"layer":"VDP_VRAM_WRITE_A",
			"row":"0A000000",
			"column":"00420000"
		},
		{
			"patternName":"Pattern24x24",
			"comment":"pattern 2 - palette 2 - base",
			"tilesetIndex":8,
			"highPriority":false,
			"paletteNumber":2,
			"repeat":0,
			"layer":"VDP_VRAM_WRITE_A",
			"row":"0A000000",
			"column":"00480000"
		},
		{
			"patternName":"Pattern24x16",
			"comment":"pattern 0 - palette 0 - high",
			"tilesetIndex":9,
			"highPriority":true,
			"paletteNumber":0,
			"repeat":0,
			"layer":"VDP_VRAM_WRITE_A",
			"row":"08800000",
			"column":"00020000"
		},
		{
			"patternName":"Pattern24x8",
			"comment":"pattern 0 - palette 0 - low",
			"tilesetIndex":9,
			"tilesetOffset":6,
			"highPriority":true,
			"paletteNumber":0,
			"repeat":0,
			"layer":"VDP_VRAM_WRITE_A",
			"row":"09800000",
			"column":"00020000"
		},
		{
			"patternName":"Pattern24x16",
			"comment":"pattern 0 - palette 0 - high",
			"tilesetIndex":9,
			"highPriority":true,
			"paletteNumber":0,
			"repeat":0,
			"layer":"VDP_VRAM_WRITE_A",
			"row":"08800000",
			"column":"00080000"
		},
		{
			"patternName":"Pattern24x8",
			"comment":"pattern 0 - palette 0 - low",
			"tilesetIndex":9,
			"tilesetOffset":6,
			"highPriority":false,
			"paletteNumber":0,
			"repeat":0,
			"layer":"VDP_VRAM_WRITE_A",
			"row":"09800000",
			"column":"00080000"
		},
		{
			"patternName":"Pattern24x24",
			"comment":"pattern 0 - palette 1 - low",
			"tilesetIndex":9,
			"highPriority":false,
			"paletteNumber":1,
			"repeat":0,
			"layer":"VDP_VRAM_WRITE_A",
			"row":"00800000",
			"column":"00420000"
		},
		{
			"patternName":"Pattern24x24",
			"comment":"pattern 0 - palette 1 - low",
			"tilesetIndex":9,
			"highPriority":false,
			"paletteNumber":1,
			"repeat":0,
			"layer":"VDP_VRAM_WRITE_A",
			"row":"00800000",
			"column":"00480000"
		},
		{
			"patternName":"Pattern24x24",
			"comment":"pattern 0 - palette 2 - low",
			"tilesetIndex":9,
			"highPriority":false,
			"paletteNumber":2,
			"repeat":0,
			"layer":"VDP_VRAM_WRITE_A",
			"row":"00800000",
			"column":"000E0000"
		},
		{
			"patternName":"Pattern24x24",
			"tilesetIndex":9,
			"highPriority":false,
			"paletteNumber":2,
			"repeat":0,
			"layer":"VDP_VRAM_WRITE_A",
			"row":"00800000",
			"column":"00140000"
		},
		{
			"patternName":"Pattern24x16",
			"comment":"pattern 1 - palette 0 - high",
			"tilesetIndex":10,
			"highPriority":true,
			"paletteNumber":0,
			"repeat":0,
			"layer":"VDP_VRAM_WRITE_A",
			"row":"04800000",
			"column":"00360000"
		},
		{
			"patternName":"Pattern24x8",
			"comment":"pattern 1 - palette 0 - low",
			"tilesetIndex":10,
			"tilesetOffset":6,
			"highPriority":false,
			"paletteNumber":0,
			"repeat":0,
			"layer":"VDP_VRAM_WRITE_A",
			"row":"05800000",
			"column":"00360000"
		},
		{
			"patternName":"Pattern24x16",
			"comment":"pattern 1 - palette 0 - high",
			"tilesetIndex":10,
			"highPriority":true,
			"paletteNumber":0,
			"repeat":0,
			"layer":"VDP_VRAM_WRITE_A",
			"row":"04800000",
			"column":"003C0000"
		},
		{
			"patternName":"Pattern24x8",
			"comment":"pattern 1 - palette 0 - low",
			"tilesetIndex":10,
			"tilesetOffset":6,
			"highPriority":false,
			"paletteNumber":0,
			"repeat":0,
			"layer":"VDP_VRAM_WRITE_A",
			"row":"05800000",
			"column":"003C0000"
		},
		{
			"patternName":"Pattern24x24",
			"comment":"pattern 1 - palette 1 - low",
			"tilesetIndex":10,
			"highPriority":false,
			"paletteNumber":1,
			"repeat":0,
			"layer":"VDP_VRAM_WRITE_A",
			"row":"00800000",
			"column":"00020000"
		},
		{
			"patternName":"Pattern24x24",
			"comment":"pattern 1 - palette 1 - low",
			"tilesetIndex":10,
			"highPriority":false,
			"paletteNumber":1,
			"repeat":0,
			"layer":"VDP_VRAM_WRITE_A",
			"row":"00800000",
			"column":"00080000"
		},
		{
			"patternName":"Pattern24x16",
			"comment":"pattern 1 - palette 2 - high",
			"tilesetIndex":10,
			"highPriority":true,
			"paletteNumber":1,
			"repeat":0,
			"layer":"VDP_VRAM_WRITE_A",
			"row":"04800000",
			"column":"000E0000"
		},
		{
			"patternName":"Pattern24x8",
			"comment":"pattern 1 - palette 2 - low",
			"tilesetIndex":10,
			"tilesetOffset":6,
			"highPriority":false,
			"paletteNumber":2,
			"repeat":0,
			"layer":"VDP_VRAM_WRITE_A",
			"row":"05800000",
			"column":"000E0000"
		},
		{
			"patternName":"Pattern24x16",
			"comment":"pattern 1 - palette 2 - high",
			"tilesetIndex":10,
			"highPriority":true,
			"paletteNumber":1,
			"repeat":0,
			"layer":"VDP_VRAM_WRITE_A",
			"row":"04800000",
			"column":"00140000"
		},
		{
			"patternName":"Pattern24x8",
			"comment":"pattern 1 - palette 2 - low",
			"tilesetIndex":10,
			"tilesetOffset":6,
			"highPriority":false,
			"paletteNumber":2,
			"repeat":0,
			"layer":"VDP_VRAM_WRITE_A",
			"row":"05800000",
			"column":"00140000"
		},
		{
			"patternName":"Pattern24x24",
			"comment":"pattern 2 - palette 0 - low",
			"tilesetIndex":11,
			"highPriority":false,
			"paletteNumber":0,
			"repeat":0,
			"layer":"VDP_VRAM_WRITE_A",
			"row":"00800000",
			"column":"00360000"
		},
		{
			"patternName":"Pattern24x24",
			"tilesetIndex":11,
			"highPriority":false,
			"paletteNumber":0,
			"repeat":0,
			"layer":"VDP_VRAM_WRITE_A",
			"row":"00800000",
			"column":"003C0000"
		},
		{
			"patternName":"Pattern24x16",
			"comment":"pattern 2 - palette 1 - high",
			"tilesetIndex":11,
			"highPriority":true,
			"paletteNumber":1,
			"repeat":0,
			"layer":"VDP_VRAM_WRITE_A",
			"row":"04800000",
			"column":"00220000"
		},
		{
			"patternName":"Pattern24x8",
			"comment":"pattern 2 - palette 1 - low",
			"tilesetIndex":11,
			"tilesetOffset":6,
			"highPriority":false,
			"paletteNumber":1,
			"repeat":0,
			"layer":"VDP_VRAM_WRITE_A",
			"row":"05800000",
			"column":"00220000"
		},
		{
			"patternName":"Pattern24x16",
			"comment":"pattern 2 - palette 1 - high",
			"tilesetIndex":11,
			"highPriority":true,
			"paletteNumber":1,
			"repeat":0,
			"layer":"VDP_VRAM_WRITE_A",
			"row":"04800000",
			"column":"00280000"
		},
		{
			"patternName":"Pattern24x8",
			"comment":"pattern 2 - palette 1 - low",
			"tilesetIndex":11,
			"tilesetOffset":6,
			"highPriority":false,
			"paletteNumber":1,
			"repeat":0,
			"layer":"VDP_VRAM_WRITE_A",
			"row":"05800000",
			"column":"00280000"
		},
		{
			"patternName":"Pattern24x16",
			"comment":"pattern 2 - palette 2 - high",
			"tilesetIndex":11,
			"highPriority":true,
			"paletteNumber":2,
			"repeat":0,
			"layer":"VDP_VRAM_WRITE_A",
			"row":"08800000",
			"column":"00420000"
		},
		{
			"patternName":"Pattern24x8",
			"comment":"pattern 2 - palette 2 - low",
			"tilesetIndex":11,
			"tilesetOffset":6,
			"highPriority":false,
			"paletteNumber":2,
			"repeat":0,
			"layer":"VDP_VRAM_WRITE_A",
			"row":"09800000",
			"column":"00420000"
		},
		{
			"patternName":"Pattern24x16",
			"comment":"pattern 2 - palette 2 - high",
			"tilesetIndex":11,
			"highPriority":true,
			"paletteNumber":2,
			"repeat":0,
			"layer":"VDP_VRAM_WRITE_A",
			"row":"08800000",
			"column":"00480000"
		},
		{
			"patternName":"Pattern24x8",
			"comment":"pattern 2 - palette 2 - low",
			"tilesetIndex":11,
			"tilesetOffset":6,
			"highPriority":false,
			"paletteNumber":2,
			"repeat":0,
			"layer":"VDP_VRAM_WRITE_A",
			"row":"09800000",
			"column":"00480000"
		}
	],
	"objects":[
		{
			"id":"OBJ_SCENE_CAVERN_ARCADE0",
			"x":135,
			"y":264,
			"width":48,
			"height":40
		},
		{
			"id":"OBJ_SCENE_CAVERN_ARCADE1",
			"x":392,
			"y":264,
			"width":48,
			"height":40
		},
		{
			"id":"OBJ_SCENE_CAVERN_ARCADE2",
			"x":183,
			"y":200,
			"width":48,
			"height":40
		},
		{
			"id":"OBJ_SCENE_CAVERN_ARCADE3",
			"x":263,
			"y":200,
			"width":48,
			"height":40
		},
		{
			"id":"OBJ_SCENE_CAVERN_ARCADE4",
			"x":343,
			"y":200,
			"width":48,
			"height":40
		},
		{
			"id":"OBJ_SCENE_CAVERN_ARCADE5",
			"x":136,
			"y":136,
			"width":48,
			"height":40
		},
		{
			"id":"OBJ_SCENE_CAVERN_ARCADE6",
			"x":183,
			"y":136,
			"width":48,
			"height":40
		},
		{
			"id":"OBJ_SCENE_CAVERN_ARCADE7",
			"x":343,
			"y":136,
			"width":48,
			"height":40
		},
		{
			"id":"OBJ_SCENE_CAVERN_ARCADE8",
			"x":392,
			"y":136,
			"width":48,
			"height":40
		},
		null
	],
	"collisionDataName":"CavernCollisionStart",
	"exitIds":[
		"SCENE_ID_EEHALL",
		"SCENE_ID_CAVERN_BACKROOM",
		"$FFFF",
		"$FFFF"
	],
	"npcLocations":[
		{
			"x":204,
			"y":240,
			"direction":"DIRECTION_DOWN",
			"movementFrequency":65535,
			"movementPatternName":"NullMovement"
		},
		{
			"x":0,
			"y":0,
			"direction":"DIRECTION_DOWN",
			"movementFrequency":65535,
			"movementPatternName":"NullMovement"
		},
		{
			"x":0,
			"y":0,
			"direction":"DIRECTION_DOWN",
			"movementFrequency":65535,
			"movementPatternName":"NullMovement"
		},
		{
			"x":0,
			"y":0,
			"direction":"DIRECTION_DOWN",
			"movementFrequency":65535,
			"movementPatternName":"NullMovement"
		}
	],
	"bgmName":"BGM_Mall"
}
